setup.py
basebox/__init__.py
basebox/bootstrap.py
basebox/build.py
basebox/cli.py
basebox/config.py
basebox/control.py
basebox/monkey.py
basebox/util.py
basebox/vagrant.py
basebox.egg-info/PKG-INFO
basebox.egg-info/SOURCES.txt
basebox.egg-info/dependency_links.txt
basebox.egg-info/entry_points.txt
basebox.egg-info/requires.txt
basebox.egg-info/top_level.txt