Metadata-Version: 1.0
Name: basebox
Version: 0.1.3
Summary: A small library for interacting with Vagrant boxes using Fabric
Home-page: https://github.com/davehughes/basebox
Author: David Hughes
Author-email: d@vidhughes.com
License: UNKNOWN
Platform: UNKNOWN
